CHANGELOG.txt
LICENSE.txt
MANIFEST.in
README.txt
setup.py
vega_color_schemes/__init__.py
vega_color_schemes.egg-info/PKG-INFO
vega_color_schemes.egg-info/SOURCES.txt
vega_color_schemes.egg-info/dependency_links.txt
vega_color_schemes.egg-info/requires.txt
vega_color_schemes.egg-info/top_level.txt