Metadata-Version: 1.1
Name: vega-color-schemes
Version: 0.0.1
Summary: A library to get Vega color schemes as lists.
Home-page: UNKNOWN
Author: Ryan Brown
Author-email: ryan.brown@utexas.edu
License: MIT
Keywords: Vega
Platform: UNKNOWN
Classifier: Development Status :: 5 - Production/Stable
Classifier: Intended Audience :: Education
Classifier: Operating System :: Microsoft :: Windows :: Windows 10
Classifier: License :: OSI Approved :: MIT License
Classifier: Programming Language :: Python :: 3
